CHANGELOG.rst
LICENSE
MANIFEST.in
README.rst
setup.cfg
setup.py
versioneer.py
pkg/__init__.py
pkg/__init__.pyc
pkg/generate_wheels.sh
pkg/pip_install_requirements.sh
pkg/requirements-latest.pip
pkg/requirements-leap.pip
pkg/requirements-testing.pip
pkg/requirements.pip
pkg/utils.py
pkg/utils.pyc
src/leap/__init__.py
src/leap.keymanager.egg-info/PKG-INFO
src/leap.keymanager.egg-info/SOURCES.txt
src/leap.keymanager.egg-info/dependency_links.txt
src/leap.keymanager.egg-info/namespace_packages.txt
src/leap.keymanager.egg-info/pbr.json
src/leap.keymanager.egg-info/requires.txt
src/leap.keymanager.egg-info/top_level.txt
src/leap/keymanager/__init__.py
src/leap/keymanager/_version.py
src/leap/keymanager/errors.py
src/leap/keymanager/keys.py
src/leap/keymanager/migrator.py
src/leap/keymanager/openpgp.py
src/leap/keymanager/validation.py