Metadata-Version: 1.1
Name: leap.keymanager
Version: 0.5.1
Summary: LEAP's Key Manager
Home-page: https://leap.se/
Author: Kali Kaneko
Author-email: kali@leap.se
License: GPLv3+
Download-URL: https://github.com/leapcode/bitmask_client/archive/0.5.1.tar.gz
Platform: UNKNOWN
Classifier: Development Status :: 4 - Beta
Classifier: Intended Audience :: Developers
Classifier: License :: OSI Approved :: GNU General Public License v3 (GPLv3)
Classifier: Operating System :: OS Independent
Classifier: Programming Language :: Python
Classifier: Programming Language :: Python :: 2.6
Classifier: Programming Language :: Python :: 2.7
Classifier: Topic :: Communications :: Email
Classifier: Topic :: Internet
Classifier: Topic :: Security :: Cryptography
Classifier: Topic :: Software Development :: Libraries
